autogoal_nltk/__init__.py
autogoal_nltk/_builder.py
autogoal_nltk/_generated.py
autogoal_nltk/_manual.py
autogoal_nltk/_utils.py
autogoal_nltk/tests/test_nltk.py
autogoal_nltk-0.8.4.dist-info/WHEEL
autogoal_nltk-0.8.4.dist-info/METADATA
autogoal_nltk-0.8.4.dist-info/RECORD
